vibe_coding_tracker/__init__.py
vibe_coding_tracker/binaries/linux-arm64-gnu/vibe_coding_tracker
vibe_coding_tracker/binaries/linux-x64-gnu/vibe_coding_tracker
vibe_coding_tracker/binaries/macos-arm64/vibe_coding_tracker
vibe_coding_tracker/binaries/macos-x64/vibe_coding_tracker
vibe_coding_tracker/binaries/windows-arm64/vibe_coding_tracker.exe
vibe_coding_tracker/binaries/windows-x64/vibe_coding_tracker.exe
vibe_coding_tracker-0.5.9.dist-info/WHEEL
vibe_coding_tracker-0.5.9.dist-info/entry_points.txt
vibe_coding_tracker-0.5.9.dist-info/METADATA
vibe_coding_tracker-0.5.9.dist-info/RECORD
